aind_flake8_extensions/__init__.py
aind_flake8_extensions/plugin.py
aind_flake8_extensions-0.6.2.dist-info/LICENSE
aind_flake8_extensions-0.6.2.dist-info/METADATA
aind_flake8_extensions-0.6.2.dist-info/WHEEL
aind_flake8_extensions-0.6.2.dist-info/top_level.txt
aind_flake8_extensions-0.6.2.dist-info/RECORD
